fds/__init__.py
fds/sdk/__init__.py
fds/sdk/OFDB/__init__.py
fds/sdk/OFDB/api_client.py
fds/sdk/OFDB/configuration.py
fds/sdk/OFDB/exceptions.py
fds/sdk/OFDB/model_utils.py
fds/sdk/OFDB/rest.py
fds/sdk/OFDB/api/__init__.py
fds/sdk/OFDB/api/add_api.py
fds/sdk/OFDB/api/create_api.py
fds/sdk/OFDB/api/delete_api.py
fds/sdk/OFDB/api/get_api.py
fds/sdk/OFDB/api/long_running_api.py
fds/sdk/OFDB/api/update_api.py
fds/sdk/OFDB/apis/__init__.py
fds/sdk/OFDB/model/__init__.py
fds/sdk/OFDB/model/add_dates.py
fds/sdk/OFDB/model/add_fields.py
fds/sdk/OFDB/model/add_symbols.py
fds/sdk/OFDB/model/bulk_delete.py
fds/sdk/OFDB/model/bulk_delete_array.py
fds/sdk/OFDB/model/bulk_delete_array_item.py
fds/sdk/OFDB/model/bulk_delete_array_item_array.py
fds/sdk/OFDB/model/bulk_delete_array_item_nested.py
fds/sdk/OFDB/model/bulk_delete_array_item_nested_array.py
fds/sdk/OFDB/model/bulk_delete_array_item_nested_object.py
fds/sdk/OFDB/model/bulk_delete_array_item_object.py
fds/sdk/OFDB/model/bulk_delete_item.py
fds/sdk/OFDB/model/content_with_date.py
fds/sdk/OFDB/model/content_with_symbol.py
fds/sdk/OFDB/model/create_database.py
fds/sdk/OFDB/model/create_database_data.py
fds/sdk/OFDB/model/data_value.py
fds/sdk/OFDB/model/database_schema.py
fds/sdk/OFDB/model/database_schema_data.py
fds/sdk/OFDB/model/date_and_content.py
fds/sdk/OFDB/model/date_and_fields.py
fds/sdk/OFDB/model/dates.py
fds/sdk/OFDB/model/dates_with_id.py
fds/sdk/OFDB/model/error_object.py
fds/sdk/OFDB/model/error_object_with_source.py
fds/sdk/OFDB/model/error_object_with_source_source.py
fds/sdk/OFDB/model/field_properties.py
fds/sdk/OFDB/model/fields.py
fds/sdk/OFDB/model/inline_response200.py
fds/sdk/OFDB/model/inline_response2001.py
fds/sdk/OFDB/model/inline_response2001_data.py
fds/sdk/OFDB/model/inline_response2002.py
fds/sdk/OFDB/model/inline_response2003.py
fds/sdk/OFDB/model/inline_response2004.py
fds/sdk/OFDB/model/inline_response2005.py
fds/sdk/OFDB/model/inline_response2006.py
fds.sdk.OFDB-0.32.1.dist-info/LICENSE
fds.sdk.OFDB-0.32.1.dist-info/METADATA
fds.sdk.OFDB-0.32.1.dist-info/WHEEL
fds.sdk.OFDB-0.32.1.dist-info/top_level.txt
fds.sdk.OFDB-0.32.1.dist-info/RECORD
